quantumchempy/__init__.py
quantumchempy/gen_basis.py
quantumchempy/utils.py
QuantumChemPy-0.2.dist-info/LICENSE
QuantumChemPy-0.2.dist-info/METADATA
QuantumChemPy-0.2.dist-info/WHEEL
QuantumChemPy-0.2.dist-info/top_level.txt
QuantumChemPy-0.2.dist-info/RECORD
