Metadata-Version: 2.1
Name: QuantumChemPy
Version: 0.2
Summary: Paquete con algunas herramientas útiles para programar teorías de química cuántica en Python
Home-page: https://github.com/felipelewyee/quantumchempy
Author: Juan Felipe Huan Lew Yee
Author-email: felipe.lew.yee@gmail.com
License: UNKNOWN
Platform: UNKNOWN
Classifier: Programming Language :: Python :: 3
Classifier: License :: OSI Approved :: GNU General Public License v3 (GPLv3)
Classifier: Operating System :: OS Independent
Requires-Python: >=3.6
Requires-Dist: numpy
